fwlipy/fwlib.py
fwlipy/setup.py
fwlipy/test.py
fwlipy/extern/fwlib/example/extern/googletest/googlemock/scripts/fuse_gmock_files.py
fwlipy/extern/fwlib/example/extern/googletest/googlemock/scripts/gmock_doctor.py
fwlipy/extern/fwlib/example/extern/googletest/googlemock/scripts/upload.py
fwlipy/extern/fwlib/example/extern/googletest/googlemock/scripts/upload_gmock.py
fwlipy/extern/fwlib/example/extern/googletest/googlemock/scripts/generator/gmock_gen.py
fwlipy/extern/fwlib/example/extern/googletest/googlemock/scripts/generator/cpp/__init__.py
fwlipy/extern/fwlib/example/extern/googletest/googlemock/scripts/generator/cpp/ast.py
fwlipy/extern/fwlib/example/extern/googletest/googlemock/scripts/generator/cpp/gmock_class.py
fwlipy/extern/fwlib/example/extern/googletest/googlemock/scripts/generator/cpp/gmock_class_test.py
fwlipy/extern/fwlib/example/extern/googletest/googlemock/scripts/generator/cpp/keywords.py
fwlipy/extern/fwlib/example/extern/googletest/googlemock/scripts/generator/cpp/tokenize.py
fwlipy/extern/fwlib/example/extern/googletest/googlemock/scripts/generator/cpp/utils.py
fwlipy/extern/fwlib/example/extern/googletest/googlemock/test/gmock-function-mocker_nc_test.py
fwlipy/extern/fwlib/example/extern/googletest/googlemock/test/gmock_leak_test.py
fwlipy/extern/fwlib/example/extern/googletest/googlemock/test/gmock_output_test.py
fwlipy/extern/fwlib/example/extern/googletest/googlemock/test/gmock_test_utils.py
fwlipy/extern/fwlib/example/extern/googletest/googletest/scripts/common.py
fwlipy/extern/fwlib/example/extern/googletest/googletest/scripts/fuse_gtest_files.py
fwlipy/extern/fwlib/example/extern/googletest/googletest/scripts/gen_gtest_pred_impl.py
fwlipy/extern/fwlib/example/extern/googletest/googletest/scripts/pump.py
fwlipy/extern/fwlib/example/extern/googletest/googletest/scripts/release_docs.py
fwlipy/extern/fwlib/example/extern/googletest/googletest/scripts/upload.py
fwlipy/extern/fwlib/example/extern/googletest/googletest/scripts/upload_gtest.py
pyfanuc-0.0.5.dist-info/LICENSE
pyfanuc-0.0.5.dist-info/METADATA
pyfanuc-0.0.5.dist-info/WHEEL
pyfanuc-0.0.5.dist-info/entry_points.txt
pyfanuc-0.0.5.dist-info/top_level.txt
pyfanuc-0.0.5.dist-info/RECORD
