Metadata-Version: 2.1
Name: pyfanuc
Version: 0.0.5
Summary: Read data from Fanuc control
Author-email: Lea Tonecja <tonejca@ift.at>
License: MIT License
Project-URL: Homepage, https://git.ift.tuwien.ac.at/lab/ift/sis/tec-lab/dmu75/pyfanuc.git
Keywords: focas,fanuc,pyfwlib
Classifier: License :: OSI Approved :: MIT License
Classifier: Programming Language :: Python
Classifier: Programming Language :: Python :: 3
Requires-Python: >=3.7
License-File: LICENSE
Requires-Dist: fwlipy
Requires-Dist: tomli ; python_version < "3.11"
Provides-Extra: dev
Requires-Dist: black ; extra == 'dev'
Requires-Dist: pip-tools ; extra == 'dev'
Requires-Dist: pytest ; extra == 'dev'
